pyhesaff/__main__.py
pyhesaff/_version.py
pyhesaff/__init__.py
pyhesaff/_pyhesaff.py
pyhesaff/ctypes_interface.py
pyhesaff/lib/libhesaff.so.4.0.0
pyhesaff/lib/libhesaff.so.4.0
pyhesaff/lib/libhesaff.so
pyhesaff/lib/libhesaff_s.a
wbia_pyhesaff-4.0.0.dist-info/LICENSE.txt
wbia_pyhesaff-4.0.0.dist-info/RECORD
wbia_pyhesaff-4.0.0.dist-info/COPYING
wbia_pyhesaff-4.0.0.dist-info/LICENSE.SIFT
wbia_pyhesaff-4.0.0.dist-info/top_level.txt
wbia_pyhesaff-4.0.0.dist-info/WHEEL
wbia_pyhesaff-4.0.0.dist-info/METADATA
wbia_pyhesaff.libs/libffi-af4ed708.so.6.0.1
wbia_pyhesaff.libs/libopencv_highgui-8bf9344d.so.2.4.5
wbia_pyhesaff.libs/libfreetype-c0e61f0c.so.6.14.0
wbia_pyhesaff.libs/liblzma-07b5b5c8.so.5.2.2
wbia_pyhesaff.libs/libXinerama-b7a62e01.so.1.0.0
wbia_pyhesaff.libs/libHalf-fab309d1.so.6.0.0
wbia_pyhesaff.libs/libgtk-x11-2-4729d4a9.0.so.0.2400.31
wbia_pyhesaff.libs/libIlmImf-779f48be.so.7.0.0
wbia_pyhesaff.libs/libpcre-9513aab5.so.1.2.0
wbia_pyhesaff.libs/libbz2-a273e504.so.1.0.6
wbia_pyhesaff.libs/libpangocairo-1-b80816ef.0.so.0.4200.3
wbia_pyhesaff.libs/libgdk-x11-2-91ff5995.0.so.0.2400.31
wbia_pyhesaff.libs/libXrandr-1b5fae8f.so.2.2.0
wbia_pyhesaff.libs/libgstapp-0-a5c3a46f.10.so.0.25.0
wbia_pyhesaff.libs/libxcb-shm-7a199f70.so.0.0.0
wbia_pyhesaff.libs/libpangoft2-1-01996ad5.0.so.0.4200.3
wbia_pyhesaff.libs/libv4l2-3017b2f2.so.0.0.0
wbia_pyhesaff.libs/libuuid-f64cda11.so.1.3.0
wbia_pyhesaff.libs/libgstvideo-0-eb93982c.10.so.0.25.0
wbia_pyhesaff.libs/libgmodule-2-ef3ece87.0.so.0.5600.1
wbia_pyhesaff.libs/libXi-e28fba09.so.6.1.0
wbia_pyhesaff.libs/libmount-2c8ae47c.so.1.1.0
wbia_pyhesaff.libs/libIexMath-ffbe7dee.so.6.0.0
wbia_pyhesaff.libs/libGLdispatch-dcc1ca97.so.0.0.0
wbia_pyhesaff.libs/libthai-b24067ec.so.0.1.6
wbia_pyhesaff.libs/libcairo-55a37961.so.2.11512.0
wbia_pyhesaff.libs/libpng15-ce838cd1.so.15.13.0
wbia_pyhesaff.libs/libXdamage-b7595c70.so.1.1.0
wbia_pyhesaff.libs/libjasper-20c9a267.so.1.0.0
wbia_pyhesaff.libs/libgstreamer-0-b9f61d5a.10.so.0.30.0
wbia_pyhesaff.libs/liborc-0-14d3dc57.4.so.0.25.0
wbia_pyhesaff.libs/libharfbuzz-77c15733.so.0.10705.0
wbia_pyhesaff.libs/libpango-1-875bd7a7.0.so.0.4200.3
wbia_pyhesaff.libs/libIex-5cfd6889.so.6.0.0
wbia_pyhesaff.libs/libjpeg-43436dd5.so.62.1.0
