Metadata-Version: 2.1
Name: wbia-pyhesaff
Version: 4.0.0
Summary: PyHesaff - Python wrapper for Hessian Affine
Home-page: https://github.com/WildbookOrg/hesaff
Author: Krystian Mikolajczyk, Michal Perdoch, Jon Crall, Avi Weinstock, WildMe Developers
Author-email: dev@wildme.org
License: APL 2.0
Platform: UNKNOWN
Classifier: Development Status :: 6 - Mature
Classifier: License :: OSI Approved :: BSD License
Classifier: Intended Audience :: Developers
Classifier: Intended Audience :: Science/Research
Classifier: Operating System :: MacOS :: MacOS X
Classifier: Operating System :: Unix
Classifier: Topic :: Software Development :: Libraries :: Python Modules
Classifier: Programming Language :: Python :: 2.7
Classifier: Programming Language :: Python :: 3.5
Classifier: Programming Language :: Python :: 3.6
Classifier: Programming Language :: Python :: 3.7
Classifier: Programming Language :: Python :: 3.8
Classifier: Topic :: Scientific/Engineering :: Artificial Intelligence
Classifier: Topic :: Scientific/Engineering :: Image Recognition
License-File: LICENSE.SIFT
License-File: LICENSE.txt
License-File: COPYING
Requires-Dist: matplotlib
Requires-Dist: opencv-contrib-python-headless
Requires-Dist: ubelt
Requires-Dist: wbia-vtool
Provides-Extra: all
Requires-Dist: cmake ; extra == 'all'
Requires-Dist: ninja ; extra == 'all'
Requires-Dist: scikit-build ; extra == 'all'
Requires-Dist: setuptools ; extra == 'all'
Requires-Dist: setuptools-scm[toml] ; extra == 'all'
Requires-Dist: wheel ; extra == 'all'
Requires-Dist: matplotlib ; extra == 'all'
Requires-Dist: opencv-contrib-python-headless ; extra == 'all'
Requires-Dist: ubelt ; extra == 'all'
Requires-Dist: wbia-vtool ; extra == 'all'
Requires-Dist: brunette ; extra == 'all'
Requires-Dist: codecov ; extra == 'all'
Requires-Dist: coverage ; extra == 'all'
Requires-Dist: pytest ; extra == 'all'
Requires-Dist: pytest-cov ; extra == 'all'
Requires-Dist: xdoctest ; extra == 'all'
Provides-Extra: build
Requires-Dist: cmake ; extra == 'build'
Requires-Dist: ninja ; extra == 'build'
Requires-Dist: scikit-build ; extra == 'build'
Requires-Dist: setuptools ; extra == 'build'
Requires-Dist: setuptools-scm[toml] ; extra == 'build'
Requires-Dist: wheel ; extra == 'build'
Provides-Extra: runtime
Requires-Dist: matplotlib ; extra == 'runtime'
Requires-Dist: opencv-contrib-python-headless ; extra == 'runtime'
Requires-Dist: ubelt ; extra == 'runtime'
Requires-Dist: wbia-vtool ; extra == 'runtime'
Provides-Extra: tests
Requires-Dist: brunette ; extra == 'tests'
Requires-Dist: codecov ; extra == 'tests'
Requires-Dist: coverage ; extra == 'tests'
Requires-Dist: pytest ; extra == 'tests'
Requires-Dist: pytest-cov ; extra == 'tests'
Requires-Dist: xdoctest ; extra == 'tests'
